ldap_filter/__init__.py
ldap_filter/filter.py
ldap_filter/parser.py
ldap_filter/soundex.py
ldap_filter-1.0.1.dist-info/LICENSE.txt
ldap_filter-1.0.1.dist-info/METADATA
ldap_filter-1.0.1.dist-info/WHEEL
ldap_filter-1.0.1.dist-info/top_level.txt
ldap_filter-1.0.1.dist-info/RECORD
