Metadata-Version: 2.1
Name: ldap-filter
Version: 1.0.1
Summary: A Python utility library for working with Lightweight Directory Access Protocol (LDAP) filters.
Author-email: Stephen Ewell <steve@ewell.io>
License: The MIT License (MIT)
Project-URL: Homepage, https://github.com/SteveEwell/python-ldap-filter
Keywords: ldap,filter,rfc4515,utility,development
Classifier: Intended Audience :: Developers
Classifier: Topic :: Software Development :: Libraries :: Python Modules
Classifier: License :: OSI Approved :: MIT License
Classifier: Programming Language :: Python
Classifier: Programming Language :: Python :: 3
Classifier: Programming Language :: Python :: 3.4
Classifier: Programming Language :: Python :: 3.5
Classifier: Programming Language :: Python :: 3.6
Classifier: Programming Language :: Python :: 3.7
Classifier: Programming Language :: Python :: 3.8
Classifier: Programming Language :: Python :: 3.9
Classifier: Programming Language :: Python :: 3.10
Classifier: Programming Language :: Python :: 3.11
Classifier: Programming Language :: Python :: 3.12
Requires-Python: >=3.4
License-File: LICENSE.txt
Provides-Extra: test
Requires-Dist: pytest; extra == "test"
Requires-Dist: coverage; extra == "test"
